ctfcli/__init__.py
ctfcli/__main__.py
ctfcli/cli/__init__.py
ctfcli/cli/challenges.py
ctfcli/cli/config.py
ctfcli/cli/instance.py
ctfcli/cli/media.py
ctfcli/cli/pages.py
ctfcli/cli/plugins.py
ctfcli/cli/templates.py
ctfcli/core/__init__.py
ctfcli/core/api.py
ctfcli/core/challenge.py
ctfcli/core/config.py
ctfcli/core/exceptions.py
ctfcli/core/image.py
ctfcli/core/media.py
ctfcli/core/page.py
ctfcli/core/plugins.py
ctfcli/core/deployment/__init__.py
ctfcli/core/deployment/base.py
ctfcli/core/deployment/cloud.py
ctfcli/core/deployment/registry.py
ctfcli/core/deployment/ssh.py
ctfcli/core/instance/__init__.py
ctfcli/core/instance/config.py
ctfcli/spec/challenge-example.yml
ctfcli/templates/binary/default/cookiecutter.json
ctfcli/templates/binary/default/{{cookiecutter.name}}/.dockerignore
ctfcli/templates/binary/default/{{cookiecutter.name}}/Makefile
ctfcli/templates/binary/default/{{cookiecutter.name}}/README.md
ctfcli/templates/binary/default/{{cookiecutter.name}}/challenge.yml
ctfcli/templates/binary/default/{{cookiecutter.name}}/src/{{cookiecutter.name}}.c
ctfcli/templates/binary/default/{{cookiecutter.name}}/writeup/WRITEUP.md
ctfcli/templates/blank/default/cookiecutter.json
ctfcli/templates/blank/default/{{cookiecutter.name}}/README.md
ctfcli/templates/blank/default/{{cookiecutter.name}}/challenge.yml
ctfcli/templates/blank/default/{{cookiecutter.name}}/src/placeholder
ctfcli/templates/blank/default/{{cookiecutter.name}}/writeup/WRITEUP.md
ctfcli/templates/blank/empty/cookiecutter.json
ctfcli/templates/blank/empty/{{cookiecutter.dirname}}/challenge.yml
ctfcli/templates/crypto/default/cookiecutter.json
ctfcli/templates/crypto/default/{{cookiecutter.name}}/.gitignore
ctfcli/templates/crypto/default/{{cookiecutter.name}}/Makefile
ctfcli/templates/crypto/default/{{cookiecutter.name}}/README.md
ctfcli/templates/crypto/default/{{cookiecutter.name}}/challenge.yml
ctfcli/templates/crypto/default/{{cookiecutter.name}}/src/encrypt.py
ctfcli-0.1.6.dist-info/METADATA
ctfcli-0.1.6.dist-info/WHEEL
ctfcli-0.1.6.dist-info/entry_points.txt
ctfcli-0.1.6.dist-info/licenses/LICENSE
ctfcli-0.1.6.dist-info/RECORD
