Metadata-Version: 2.4
Name: ctfcli
Version: 0.1.6
Summary: ctfcli is a tool to manage Capture The Flag events and challenges
Author-email: Kevin Chung <kchung@ctfd.io>, Miłosz Skaza <milosz.skaza@ctfd.io>
License-File: LICENSE
Requires-Python: <4,>=3.10
Requires-Dist: appdirs<2,>=1.4.4
Requires-Dist: click<9,>=8.1.7
Requires-Dist: colorama<0.5,>=0.4.6
Requires-Dist: cookiecutter<3,>=2.3.0
Requires-Dist: fire<0.8,>=0.7.0
Requires-Dist: python-frontmatter<2,>=1.0.0
Requires-Dist: python-slugify<9,>=8.0.4
Requires-Dist: pyyaml<7,>=6.0.1
Requires-Dist: requests<3,>=2.31.0
Requires-Dist: typing-extensions<5,>=4.7.1
